pywhereisrunning/__init__.py
pywhereisrunning/main.py
pywhereisrunning/pywhereisrunning.py
pywhereisrunning/utils.py
pywhereisrunning-0.0.2.dist-info/METADATA
pywhereisrunning-0.0.2.dist-info/WHEEL
pywhereisrunning-0.0.2.dist-info/entry_points.txt
pywhereisrunning-0.0.2.dist-info/top_level.txt
pywhereisrunning-0.0.2.dist-info/RECORD
